textual_slider/__init__.py
textual_slider/_slider.py
textual_slider/py.typed
textual_slider-0.2.0.dist-info/LICENSE
textual_slider-0.2.0.dist-info/METADATA
textual_slider-0.2.0.dist-info/WHEEL
textual_slider-0.2.0.dist-info/top_level.txt
textual_slider-0.2.0.dist-info/RECORD
